litraj/README.md
litraj/__init__.py
litraj/data.py
litraj/metrics.py
litraj/utils.py
litraj-0.1.dist-info/LICENSE
litraj-0.1.dist-info/METADATA
litraj-0.1.dist-info/WHEEL
litraj-0.1.dist-info/top_level.txt
litraj-0.1.dist-info/zip-safe
litraj-0.1.dist-info/RECORD
