Metadata-Version: 2.1
Name: litraj
Version: 0.1
Summary: LiTraj: Li-ion migration dataset
Home-page: https://github.com/AIRI-Institute/LiTraj
Author: Artem Dembitskiy
Author-email: art.dembitskiy@gmail.com
License: MIT
Keywords: Li-ion,migration-barrier,DFT,machine-learning,dataset,benchmark,universal-potential
Platform: UNKNOWN
Classifier: Programming Language :: Python :: 3
Classifier: License :: OSI Approved :: MIT License
Classifier: Operating System :: OS Independent
License-File: LICENSE
Requires-Dist: requests
Requires-Dist: pandas
Requires-Dist: numpy
Requires-Dist: scipy
Requires-Dist: ase
Requires-Dist: tqdm
